README.md
setup.cfg
setup.py
nuvo_tuner/__init__.py
nuvo_tuner.egg-info/PKG-INFO
nuvo_tuner.egg-info/SOURCES.txt
nuvo_tuner.egg-info/dependency_links.txt
nuvo_tuner.egg-info/requires.txt
nuvo_tuner.egg-info/top_level.txt