Metadata-Version: 2.1
Name: nuvo_tuner
Version: 0.9
Summary: Python API for talking to Nuvo radio tuners
Home-page: https://github.com/brmccrary/pynuvo_tuner
Author: bmccrary
Author-email: bmccrary@shcircuit.com
Classifier: Programming Language :: Python :: 3
Classifier: License :: OSI Approved :: MIT License
Classifier: Operating System :: OS Independent
Requires-Dist: pyserial>=3.4
